dynamic_conf/__init__.py
dynamic_conf/_conf.py
dynamic_conf/_env.py
dynamic_conf/_import.py
dynamic_conf-1.1.0.dist-info/METADATA
dynamic_conf-1.1.0.dist-info/WHEEL
dynamic_conf-1.1.0.dist-info/entry_points.txt
dynamic_conf-1.1.0.dist-info/licenses/LICENSE
dynamic_conf-1.1.0.dist-info/RECORD
