Metadata-Version: 2.4
Name: dynamic-conf
Version: 1.1.0
Summary: Easy to manage Config variables separate from App code. Useful while developing and deploying( CI/CD) django web-apps
Project-URL: Homepage, https://github.com/jnoortheen/dynamic-conf
Project-URL: Repository, https://github.com/jnoortheen/dynamic-conf
Author-email: Noortheen Raja <jnoortheen@gmail.com>
License-Expression: MIT
License-File: LICENSE
Keywords: 12 factor settings,configuration,django
Classifier: Framework :: Django
Classifier: Intended Audience :: Developers
Classifier: License :: OSI Approved :: MIT License
Classifier: Natural Language :: English
Classifier: Operating System :: OS Independent
Classifier: Programming Language :: Python
Classifier: Topic :: Software Development :: Libraries
Classifier: Topic :: Software Development :: Libraries :: Python Modules
Classifier: Topic :: Utilities
Requires-Python: >=3.8
Requires-Dist: arger<2,>=1.0.10
Provides-Extra: dev
Requires-Dist: better-exceptions; extra == 'dev'
Requires-Dist: ipython; extra == 'dev'
Requires-Dist: pytest; extra == 'dev'
Requires-Dist: pytest-cov; extra == 'dev'
Requires-Dist: sniffer; extra == 'dev'
Requires-Dist: tox; extra == 'dev'
